skyway/__init__.py
skyway/canvas.py
skyway/utils.py
skyway/query/__init__.py
skyway/query/base.py
skyway/query/filters.py
skyway/query/formats.py
skyway/query/query.py
skyway/query/scrape.py
skyway/query/settings.py
skyway_test-0.0.1.dist-info/LICENSE
skyway_test-0.0.1.dist-info/METADATA
skyway_test-0.0.1.dist-info/WHEEL
skyway_test-0.0.1.dist-info/top_level.txt
skyway_test-0.0.1.dist-info/RECORD
